arwell/__init__.py
arwell/cli.py
arwell/open_blog.py
arwell/rename.py
arwell-0.1.4.dist-info/licenses/LICENSE
arwell-0.1.4.dist-info/METADATA
arwell-0.1.4.dist-info/WHEEL
arwell-0.1.4.dist-info/entry_points.txt
arwell-0.1.4.dist-info/top_level.txt
arwell-0.1.4.dist-info/RECORD
